{
  "method": "ticker-level response and spread metrics from ROUND_3 prices tape",
  "by_day": {
    "0": {
      "VEV_4000": {
        "n": 9999,
        "beta1": 0.7444740196753732,
        "corr": 0.595206186767813,
        "beta_up": 0.6075438779989262,
        "beta_down": 0.6389066325260186,
        "corr_dO_t_dS_t_minus_1": -0.01891563760528614,
        "corr_dO_t_dS_t_plus_1": -0.015396412093787042,
        "spread_mean": 20.765476547654764,
        "spread_mean_shock": 20.76916802610114,
        "spread_shock_ratio": 1.000177769984614,
        "shock_threshold_abs_dS": 2.0
      },
      "VEV_4500": {
        "n": 9999,
        "beta1": 0.6598429866033918,
        "corr": 0.595975009247409,
        "beta_up": 0.5363464185764932,
        "beta_down": 0.5963447177116364,
        "corr_dO_t_dS_t_minus_1": 0.01694440295278836,
        "corr_dO_t_dS_t_plus_1": 0.015234328969797477,
        "spread_mean": 15.784178417841785,
        "spread_mean_shock": 15.765905383360522,
        "spread_shock_ratio": 0.9988423195685239,
        "shock_threshold_abs_dS": 2.0
      },
      "VEV_5000": {
        "n": 9999,
        "beta1": 0.6506629608666915,
        "corr": 0.7544675058972928,
        "beta_up": 0.5230583432685355,
        "beta_down": 0.5590135056819058,
        "corr_dO_t_dS_t_minus_1": 0.0005539083171282353,
        "corr_dO_t_dS_t_plus_1": -0.0030026815532810548,
        "spread_mean": 6.001800180018002,
        "spread_mean_shock": 5.987765089722675,
        "spread_shock_ratio": 0.9976615198983042,
        "shock_threshold_abs_dS": 2.0
      },
      "VEV_5100": {
        "n": 9999,
        "beta1": 0.5606951705169014,
        "corr": 0.7597488181369673,
        "beta_up": 0.4623146611744465,
        "beta_down": 0.4788953943178738,
        "corr_dO_t_dS_t_minus_1": 0.0004853506862789826,
        "corr_dO_t_dS_t_plus_1": -0.0036973803438071734,
        "spread_mean": 4.31973197319732,
        "spread_mean_shock": 4.311582381729201,
        "spread_shock_ratio": 0.9981134034429253,
        "shock_threshold_abs_dS": 2.0
      },
      "VEV_5200": {
        "n": 9999,
        "beta1": 0.4299851007798906,
        "corr": 0.7093899564795132,
        "beta_up": 0.343081333851574,
        "beta_down": 0.38696244455266426,
        "corr_dO_t_dS_t_minus_1": -0.001807675902856574,
        "corr_dO_t_dS_t_plus_1": -0.0018731406897959382,
        "spread_mean": 2.925992599259926,
        "spread_mean_shock": 2.930668841761827,
        "spread_shock_ratio": 1.001598173044964,
        "shock_threshold_abs_dS": 2.0
      },
      "VEV_5300": {
        "n": 9999,
        "beta1": 0.27364669121562585,
        "corr": 0.6252196719397927,
        "beta_up": 0.21855632257226681,
        "beta_down": 0.23539030737601063,
        "corr_dO_t_dS_t_minus_1": 0.008326212518117522,
        "corr_dO_t_dS_t_plus_1": -0.005414911735598274,
        "spread_mean": 2.1606160616061607,
        "spread_mean_shock": 2.1508972267536706,
        "spread_shock_ratio": 0.9955018223620603,
        "shock_threshold_abs_dS": 2.0
      },
      "VEV_5400": {
        "n": 9999,
        "beta1": 0.1378586639014525,
        "corr": 0.5594821054220038,
        "beta_up": 0.12212268191477867,
        "beta_down": 0.12247919278815536,
        "corr_dO_t_dS_t_minus_1": 0.0021007092778855905,
        "corr_dO_t_dS_t_plus_1": -0.01398252864013862,
        "spread_mean": 1.4296429642964297,
        "spread_mean_shock": 1.4265905383360522,
        "spread_shock_ratio": 0.9978649033104012,
        "shock_threshold_abs_dS": 2.0
      },
      "VEV_5500": {
        "n": 9999,
        "beta1": 0.06382170773197818,
        "corr": 0.3753313287877714,
        "beta_up": 0.061422561597606964,
        "beta_down": 0.05570149556311135,
        "corr_dO_t_dS_t_minus_1": 0.0057386022423453744,
        "corr_dO_t_dS_t_plus_1": -0.0029280374336649877,
        "spread_mean": 1.1807180718071808,
        "spread_mean_shock": 1.1949429037520392,
        "spread_shock_ratio": 1.0120476109280567,
        "shock_threshold_abs_dS": 2.0
      },
      "VEV_6000": {
        "n": 9999,
        "beta1": 0.0,
        "corr": null,
        "beta_up": 0.0,
        "beta_down": 0.0,
        "corr_dO_t_dS_t_minus_1": null,
        "corr_dO_t_dS_t_plus_1": null,
        "spread_mean": 1.0,
        "spread_mean_shock": 1.0,
        "spread_shock_ratio": 1.0,
        "shock_threshold_abs_dS": 2.0
      },
      "VEV_6500": {
        "n": 9999,
        "beta1": 0.0,
        "corr": null,
        "beta_up": 0.0,
        "beta_down": 0.0,
        "corr_dO_t_dS_t_minus_1": null,
        "corr_dO_t_dS_t_plus_1": null,
        "spread_mean": 1.0,
        "spread_mean_shock": 1.0,
        "spread_shock_ratio": 1.0,
        "shock_threshold_abs_dS": 2.0
      }
    },
    "1": {
      "VEV_4000": {
        "n": 9999,
        "beta1": 0.7582068330615972,
        "corr": 0.5994664140190595,
        "beta_up": 0.6466897156530114,
        "beta_down": 0.6501300482358668,
        "corr_dO_t_dS_t_minus_1": -0.029138516969844538,
        "corr_dO_t_dS_t_plus_1": -0.04963132914576514,
        "spread_mean": 20.774577457745774,
        "spread_mean_shock": 20.7710100231303,
        "spread_shock_ratio": 0.9998282788363456,
        "shock_threshold_abs_dS": 2.0
      },
      "VEV_4500": {
        "n": 9999,
        "beta1": 0.6658889826687833,
        "corr": 0.5964546795829306,
        "beta_up": 0.5652169847633235,
        "beta_down": 0.5793534027348278,
        "corr_dO_t_dS_t_minus_1": 0.005353716063514263,
        "corr_dO_t_dS_t_plus_1": -0.009185952348825839,
        "spread_mean": 15.812881288128812,
        "spread_mean_shock": 15.813415574402468,
        "spread_shock_ratio": 1.000033788040517,
        "shock_threshold_abs_dS": 2.0
      },
      "VEV_5000": {
        "n": 9999,
        "beta1": 0.652066051389406,
        "corr": 0.7516312031905498,
        "beta_up": 0.5269425739506421,
        "beta_down": 0.5445300872298465,
        "corr_dO_t_dS_t_minus_1": -0.013141070185669092,
        "corr_dO_t_dS_t_plus_1": -0.01781840673299464,
        "spread_mean": 6.008200820082008,
        "spread_mean_shock": 5.989976869699306,
        "spread_shock_ratio": 0.9969668206958413,
        "shock_threshold_abs_dS": 2.0
      },
      "VEV_5100": {
        "n": 9999,
        "beta1": 0.575960438743891,
        "corr": 0.76823441208884,
        "beta_up": 0.4620802626633958,
        "beta_down": 0.49534500647298324,
        "corr_dO_t_dS_t_minus_1": -0.019659909122906168,
        "corr_dO_t_dS_t_plus_1": -0.023958684915277348,
        "spread_mean": 4.257025702570257,
        "spread_mean_shock": 4.254433307633,
        "spread_shock_ratio": 0.9993910314105711,
        "shock_threshold_abs_dS": 2.0
      },
      "VEV_5200": {
        "n": 9999,
        "beta1": 0.4320580742517587,
        "corr": 0.7115237775470147,
        "beta_up": 0.3615303965334389,
        "beta_down": 0.35991861837842415,
        "corr_dO_t_dS_t_minus_1": -0.01627821892676403,
        "corr_dO_t_dS_t_plus_1": -0.01407175609353824,
        "spread_mean": 2.877887788778878,
        "spread_mean_shock": 2.87124132613724,
        "spread_shock_ratio": 0.9976905066738344,
        "shock_threshold_abs_dS": 2.0
      },
      "VEV_5300": {
        "n": 9999,
        "beta1": 0.27103121053065743,
        "corr": 0.6173352247495307,
        "beta_up": 0.21951817593262737,
        "beta_down": 0.22878409673436756,
        "corr_dO_t_dS_t_minus_1": -0.011455807999643547,
        "corr_dO_t_dS_t_plus_1": -0.006769496783622282,
        "spread_mean": 2.1088108810881088,
        "spread_mean_shock": 2.1010023130300692,
        "spread_shock_ratio": 0.9962971700648612,
        "shock_threshold_abs_dS": 2.0
      },
      "VEV_5400": {
        "n": 9999,
        "beta1": 0.12701219741929512,
        "corr": 0.5362954165289172,
        "beta_up": 0.10113238160687116,
        "beta_down": 0.10020066378705311,
        "corr_dO_t_dS_t_minus_1": -0.012297432968609055,
        "corr_dO_t_dS_t_plus_1": -0.018199472507565706,
        "spread_mean": 1.3864386438643865,
        "spread_mean_shock": 1.374710871241326,
        "spread_shock_ratio": 0.9915410806854229,
        "shock_threshold_abs_dS": 2.0
      },
      "VEV_5500": {
        "n": 9999,
        "beta1": 0.054264805242901476,
        "corr": 0.34694885930271563,
        "beta_up": 0.0457856049664066,
        "beta_down": 0.038780088341593535,
        "corr_dO_t_dS_t_minus_1": 0.0012424322617247917,
        "corr_dO_t_dS_t_plus_1": 0.019986374413881743,
        "spread_mean": 1.1527152715271527,
        "spread_mean_shock": 1.141094834232845,
        "spread_shock_ratio": 0.9899190740494723,
        "shock_threshold_abs_dS": 2.0
      },
      "VEV_6000": {
        "n": 9999,
        "beta1": 0.0,
        "corr": null,
        "beta_up": 0.0,
        "beta_down": 0.0,
        "corr_dO_t_dS_t_minus_1": null,
        "corr_dO_t_dS_t_plus_1": null,
        "spread_mean": 1.0,
        "spread_mean_shock": 1.0,
        "spread_shock_ratio": 1.0,
        "shock_threshold_abs_dS": 2.0
      },
      "VEV_6500": {
        "n": 9999,
        "beta1": 0.0,
        "corr": null,
        "beta_up": 0.0,
        "beta_down": 0.0,
        "corr_dO_t_dS_t_minus_1": null,
        "corr_dO_t_dS_t_plus_1": null,
        "spread_mean": 1.0,
        "spread_mean_shock": 1.0,
        "spread_shock_ratio": 1.0,
        "shock_threshold_abs_dS": 2.0
      }
    },
    "2": {
      "VEV_4000": {
        "n": 9999,
        "beta1": 0.7325377729820705,
        "corr": 0.5899479168609381,
        "beta_up": 0.6600461249561481,
        "beta_down": 0.5651729517045647,
        "corr_dO_t_dS_t_minus_1": -0.02413724653324892,
        "corr_dO_t_dS_t_plus_1": -0.013689450148534706,
        "spread_mean": 20.9004900490049,
        "spread_mean_shock": 20.893995552260932,
        "spread_shock_ratio": 0.9996892658148808,
        "shock_threshold_abs_dS": 2.0
      },
      "VEV_4500": {
        "n": 9999,
        "beta1": 0.6596055681454439,
        "corr": 0.6013099350634853,
        "beta_up": 0.5812889483627709,
        "beta_down": 0.5120223416462408,
        "corr_dO_t_dS_t_minus_1": 0.0069811678857313,
        "corr_dO_t_dS_t_plus_1": 0.018052980805230222,
        "spread_mean": 15.96089608960896,
        "spread_mean_shock": 15.943661971830986,
        "spread_shock_ratio": 0.9989202286838272,
        "shock_threshold_abs_dS": 2.0
      },
      "VEV_5000": {
        "n": 9999,
        "beta1": 0.6577334746952488,
        "corr": 0.7548610096169349,
        "beta_up": 0.5536846013950918,
        "beta_down": 0.5347154419103618,
        "corr_dO_t_dS_t_minus_1": -0.00543602519601972,
        "corr_dO_t_dS_t_plus_1": 0.003427429509315796,
        "spread_mean": 6.12001200120012,
        "spread_mean_shock": 6.140103780578206,
        "spread_shock_ratio": 1.0032829640487873,
        "shock_threshold_abs_dS": 2.0
      },
      "VEV_5100": {
        "n": 9999,
        "beta1": 0.5948213298602755,
        "corr": 0.7681361424458122,
        "beta_up": 0.5095842779211417,
        "beta_down": 0.49232054711741496,
        "corr_dO_t_dS_t_minus_1": -0.014692926813191122,
        "corr_dO_t_dS_t_plus_1": -0.004644876382375323,
        "spread_mean": 4.310731073107311,
        "spread_mean_shock": 4.275018532246108,
        "spread_shock_ratio": 0.991715432891651,
        "shock_threshold_abs_dS": 2.0
      },
      "VEV_5200": {
        "n": 9999,
        "beta1": 0.4477041889748155,
        "corr": 0.7309421620772034,
        "beta_up": 0.38015777938174156,
        "beta_down": 0.3675974837215934,
        "corr_dO_t_dS_t_minus_1": -0.007949320506798599,
        "corr_dO_t_dS_t_plus_1": 0.0008136053101228886,
        "spread_mean": 2.86038603860386,
        "spread_mean_shock": 2.8739807264640476,
        "spread_shock_ratio": 1.004752745845041,
        "shock_threshold_abs_dS": 2.0
      },
      "VEV_5300": {
        "n": 9999,
        "beta1": 0.2734070063590506,
        "corr": 0.6224609818894458,
        "beta_up": 0.22224900449317928,
        "beta_down": 0.22726862256502875,
        "corr_dO_t_dS_t_minus_1": -0.001365835324035921,
        "corr_dO_t_dS_t_plus_1": 0.005184773341555807,
        "spread_mean": 2.051005100510051,
        "spread_mean_shock": 2.054855448480356,
        "spread_shock_ratio": 1.0018772980961126,
        "shock_threshold_abs_dS": 2.0
      },
      "VEV_5400": {
        "n": 9999,
        "beta1": 0.12200310143698458,
        "corr": 0.5243896293641809,
        "beta_up": 0.09605867225687865,
        "beta_down": 0.10022431610323122,
        "corr_dO_t_dS_t_minus_1": 0.007050131824029184,
        "corr_dO_t_dS_t_plus_1": 0.014189711455642769,
        "spread_mean": 1.3281328132813282,
        "spread_mean_shock": 1.3372868791697554,
        "spread_shock_ratio": 1.0068924325917459,
        "shock_threshold_abs_dS": 2.0
      },
      "VEV_5500": {
        "n": 9999,
        "beta1": 0.04677443089781218,
        "corr": 0.3211305586257116,
        "beta_up": 0.038115511429311834,
        "beta_down": 0.033119173552596734,
        "corr_dO_t_dS_t_minus_1": 0.009409552095290886,
        "corr_dO_t_dS_t_plus_1": 0.0017224210411965046,
        "spread_mean": 1.115911591159116,
        "spread_mean_shock": 1.133432171979244,
        "spread_shock_ratio": 1.0157006889783526,
        "shock_threshold_abs_dS": 2.0
      },
      "VEV_6000": {
        "n": 9999,
        "beta1": 0.0,
        "corr": null,
        "beta_up": 0.0,
        "beta_down": 0.0,
        "corr_dO_t_dS_t_minus_1": null,
        "corr_dO_t_dS_t_plus_1": null,
        "spread_mean": 1.0,
        "spread_mean_shock": 1.0,
        "spread_shock_ratio": 1.0,
        "shock_threshold_abs_dS": 2.0
      },
      "VEV_6500": {
        "n": 9999,
        "beta1": 0.0,
        "corr": null,
        "beta_up": 0.0,
        "beta_down": 0.0,
        "corr_dO_t_dS_t_minus_1": null,
        "corr_dO_t_dS_t_plus_1": null,
        "spread_mean": 1.0,
        "spread_mean_shock": 1.0,
        "spread_shock_ratio": 1.0,
        "shock_threshold_abs_dS": 2.0
      }
    }
  }
}